ice/__init__.py
ice/agent.py
ice/cache.py
ice/cli_utils.py
ice/environment.py
ice/execution_context.py
ice/json_value.py
ice/logging.py
ice/mode.py
ice/paper.py
ice/py.typed
ice/recipe.py
ice/server.py
ice/settings.py
ice/sqlite_shelf.py
ice/summarize.py
ice/trace.py
ice/utils.py
ice/version.py
ice/agents/approval.py
ice/agents/augmented.py
ice/agents/base.py
ice/agents/cached.py
ice/agents/fake.py
ice/agents/human.py
ice/agents/openai.py
ice/agents/openai_reasoning.py
ice/agents/ought_inference.py
ice/agents/squad.py
ice/agents/tfew.py
ice/apis/__init__.py
ice/apis/openai.py
ice/datasets/qasper.py
ice/evaluation/evaluate_recipe_result.py
ice/evaluation/evaluation_report.py
ice/evaluation/summarize_experiment_evals.py
ice/evaluation/utils.py
ice/formatter/__init__.py
ice/formatter/multi.py
ice/formatter/transform/__init__.py
ice/formatter/transform/dependent.py
ice/formatter/transform/positional.py
ice/formatter/transform/value.py
ice/metrics/__init__.py
ice/metrics/base.py
ice/metrics/gold_paragraphs.py
ice/metrics/gold_standards.py
ice/metrics/nubia.py
ice/metrics/qasper.py
ice/metrics/rouge.py
ice/nn/__init__.py
ice/nn/bert_t5_t0_ensemble.py
ice/nn/bert_t5_t0_example.py
ice/nn/tfew.py
ice/nn/weights/README.md
ice/recipes/__init__.py
ice/recipes/abstract_qa.py
ice/recipes/adherence_keyword_baseline.py
ice/recipes/adherence_simple.py
ice/recipes/adherence_tfew_paragraph.py
ice/recipes/all_quotes.py
ice/recipes/best_completion.py
ice/recipes/blinding_dynamic.py
ice/recipes/combine_abstract_answers.py
ice/recipes/comparisons_qa.py
ice/recipes/evaluate_result.py
ice/recipes/evaluate_results.py
ice/recipes/experiment_arms.py
ice/recipes/find_best_few_shot_prompt.py
ice/recipes/funnel_simple.py
ice/recipes/placebo_description.py
ice/recipes/placebo_dialogs.py
ice/recipes/placebo_keyword_baseline.py
ice/recipes/placebo_simple.py
ice/recipes/placebo_tree.py
ice/recipes/rank_paragraphs.py
ice/recipes/single_prompt.py
ice/recipes/subrecipe_example.py
ought_ice-0.5.0.dist-info/LICENSE.md
ought_ice-0.5.0.dist-info/METADATA
ought_ice-0.5.0.dist-info/WHEEL
ought_ice-0.5.0.dist-info/top_level.txt
ought_ice-0.5.0.dist-info/RECORD
