Metadata-Version: 2.1
Name: ought-ice
Version: 0.5.0
Summary: Interactive Composition Explorer
Home-page: https://github.com/oughtinc/ice
Author: Ought
Author-email: team@ought.org
License: MIT
Classifier: Programming Language :: Python :: 3.9
Classifier: Programming Language :: Python :: 3.10
Classifier: Programming Language :: Python :: 3.11
Classifier: License :: OSI Approved :: MIT License
Requires-Python: >=3.9
Provides-Extra: dev
Provides-Extra: torch
License-File: LICENSE.md
